veryfasttree/__init__.py
veryfasttree/__main__.py
veryfasttree/bin/VeryFastTree-sse2
veryfasttree-4.0.4.1.dist-info/LICENSE
veryfasttree-4.0.4.1.dist-info/METADATA
veryfasttree-4.0.4.1.dist-info/WHEEL
veryfasttree-4.0.4.1.dist-info/RECORD
