Metadata-Version: 2.1
Name: veryfasttree
Version: 4.0.4.1
Summary: Efficient phylogenetic tree inference for massive taxonomic datasets
Home-page: https://github.com/citiususc/veryfasttree
License: LGPL-3.0-only
Keywords: Phylogenetics,Sequence analysis
Author: Cesar Pomar
Author-email: cesaralfredo.pineiro@usc.es
Requires-Python: >=3.8,<4.0
Classifier: License :: OSI Approved :: GNU Lesser General Public License v3 (LGPLv3)
Classifier: Programming Language :: Python :: 3
Classifier: Programming Language :: Python :: 3.8
Classifier: Programming Language :: Python :: 3.9
Classifier: Programming Language :: Python :: 3.10
Classifier: Programming Language :: Python :: 3.11
Classifier: Programming Language :: Python :: 3.12
Requires-Dist: py-cpuinfo (>=9.0,<10.0)
Project-URL: Repository, https://github.com/citiususc/veryfasttree
